youtube/__init__.py
youtube/youtube.py
youtube/exceptions/__init__.py
youtube/exceptions/subscription.py
youtube/models/__init__.py
youtube/models/activity.py
youtube/models/activity_type.py
youtube/models/caption.py
youtube/models/channel.py
youtube/models/channel_banner.py
youtube/models/channel_section.py
youtube/models/comment.py
youtube/models/comment_thread.py
youtube/models/content_details.py
youtube/models/language.py
youtube/models/localized.py
youtube/models/playlist.py
youtube/models/playlist_item.py
youtube/models/rating.py
youtube/models/region.py
youtube/models/resource.py
youtube/models/resource_id.py
youtube/models/resource_type.py
youtube/models/scopes.py
youtube/models/search.py
youtube/models/snippet.py
youtube/models/status.py
youtube/models/subscription.py
youtube/models/thumbnail.py
youtube/models/video.py
youtube/models/video_abuse_report_reason.py
youtube/models/video_category.py
youtube/models/watermark.py
youtube/resources/__init__.py
youtube/resources/resource.py
youtube/resources/activity/__init__.py
youtube/resources/activity/activity.py
youtube/resources/channel/__init__.py
youtube/resources/channel/channel.py
youtube/resources/comment_thread/__init__.py
youtube/resources/comment_thread/comment.py
youtube/resources/comment_thread/comment_thread.py
youtube/resources/playlist/__init__.py
youtube/resources/playlist/playlist.py
youtube/resources/playlist/playlist_iterators.py
youtube/resources/playlist/utils.py
youtube/resources/playlist_item/__init__.py
youtube/resources/playlist_item/playlist_item.py
youtube/resources/playlist_item/playlist_items_iterator.py
youtube/resources/search/__init__.py
youtube/resources/search/search.py
youtube/resources/subscription/__init__.py
youtube/resources/subscription/subscription.py
youtube/resources/video/__init__.py
youtube/resources/video/video.py
youtube/schemas/__init__.py
youtube/schemas/activity.py
youtube/schemas/channel.py
youtube/schemas/channel_section.py
youtube/schemas/comment_thread.py
oryks_youtube-0.14.1.dist-info/LICENSE
oryks_youtube-0.14.1.dist-info/METADATA
oryks_youtube-0.14.1.dist-info/WHEEL
oryks_youtube-0.14.1.dist-info/top_level.txt
oryks_youtube-0.14.1.dist-info/RECORD
