Metadata-Version: 2.1
Name: oryks-youtube
Version: 0.14.1
Summary: A python library that wraps around the YouTube V3 API. You can use it find and manage YouTube resources including Videos, Playlists, Channels and Comments.
Home-page: https://youtube-wrapper.readthedocs.io/en/latest/index.html
Author: Lyle Okoth
Author-email: lyceokoth@gmail.com
License: MIT
Keywords: youtube,youtube-api,youtube comments,youtube videos,youtube channels,youtube comment thread,create youtube playlist
Platform: UNKNOWN
Classifier: Intended Audience :: Developers
Classifier: License :: OSI Approved :: MIT License
Classifier: Programming Language :: Python
Classifier: Programming Language :: Python :: 3
Classifier: Programming Language :: Python :: 3.11
Classifier: Programming Language :: Python :: 3.12
Classifier: Operating System :: OS Independent
License-File: LICENSE
Requires-Dist: oryks-google-oauth
Requires-Dist: pydantic
Requires-Dist: pydantic-settings
